{
    "reviews": [
        {
            "name": "Aditya Kumar",
            "trip": "Hawaii",
            "gender": "Male",
            "age": "17",
            "answer": "RideConnect is a game-changer for travel enthusiasts! Seamless booking, reliable transportation options, and user-friendly interface. Effortlessly plan your journey with this innovative travel platform. Highly recommended!" ,
            "id": "1"
        },
        {
            "name": "Keertan Kuppili",
            "trip": "shimla",
            "gender": "Male",
            "age": "18",
            "answer": "Experience travel like never before with RideConnect! This user-friendly website offers a diverse range of transportation options, making trip planning a breeze. Reliable, efficient, and highly recommended for wanderlust seekers!",
            "id": "2"
        }
    ]
}

